hello_dada/__init__.py
hello_dada/common.py
hello_dada/hello_dada.py
hello_dada-0.0.1.dist-info/LICENSE
hello_dada-0.0.1.dist-info/METADATA
hello_dada-0.0.1.dist-info/WHEEL
hello_dada-0.0.1.dist-info/entry_points.txt
hello_dada-0.0.1.dist-info/top_level.txt
hello_dada-0.0.1.dist-info/RECORD
